sqlalchemy_sqlany/__init__.py
sqlalchemy_sqlany/base.py
sqlalchemy_sqlany-1.0.3.dist-info/METADATA
sqlalchemy_sqlany-1.0.3.dist-info/RECORD
sqlalchemy_sqlany-1.0.3.dist-info/WHEEL
sqlalchemy_sqlany-1.0.3.dist-info/entry_points.txt
sqlalchemy_sqlany-1.0.3.dist-info/top_level.txt
test/__init__.py
test/conftest.py
test/requirements.py
test/test_suite.py
