Metadata-Version: 2.1
Name: sqlalchemy-sqlany
Version: 1.0.3
Summary: SAP Sybase SQL Anywhere dialect for SQLAlchemy
Home-page: https://github.com/sqlanywhere/sqlalchemy-sqlany
Author: Graeme Perrow
Author-email: graeme.perrow@sap.com
License: Apache 2.0
Keywords: SAP Sybase SQLAnywhere SQLAlchemy
Platform: UNKNOWN
Classifier: Development Status :: 5 - Production/Stable
Classifier: Intended Audience :: Developers
Classifier: License :: OSI Approved :: Apache Software License
Classifier: Natural Language :: English
Classifier: Operating System :: OS Independent
Classifier: Programming Language :: Python :: 2
Classifier: Programming Language :: Python :: 2.4
Classifier: Programming Language :: Python :: 2.5
Classifier: Programming Language :: Python :: 2.6
Classifier: Programming Language :: Python :: 2.7
Classifier: Programming Language :: Python :: 3
Classifier: Programming Language :: Python :: 3.4
Classifier: Programming Language :: Python :: 3.5
Classifier: Programming Language :: Python :: 3.6
Classifier: Topic :: Database
Classifier: Topic :: Software Development :: Libraries :: Python Modules
Requires-Dist: sqlanydb (>=1.0.6)
